odoo/addons/l10n_fr_department_delivery/README.rst
odoo/addons/l10n_fr_department_delivery/__init__.py
odoo/addons/l10n_fr_department_delivery/__manifest__.py
odoo/addons/l10n_fr_department_delivery/i18n/l10n_fr_department_delivery.pot
odoo/addons/l10n_fr_department_delivery/models/__init__.py
odoo/addons/l10n_fr_department_delivery/models/delivery_carrier.py
odoo/addons/l10n_fr_department_delivery/readme/CONTRIBUTORS.rst
odoo/addons/l10n_fr_department_delivery/readme/DESCRIPTION.rst
odoo/addons/l10n_fr_department_delivery/static/description/icon.png
odoo/addons/l10n_fr_department_delivery/static/description/index.html
odoo/addons/l10n_fr_department_delivery/views/delivery_carrier.xml
odoo14_addon_l10n_fr_department_delivery-14.0.1.0.1.dev4.dist-info/METADATA
odoo14_addon_l10n_fr_department_delivery-14.0.1.0.1.dev4.dist-info/WHEEL
odoo14_addon_l10n_fr_department_delivery-14.0.1.0.1.dev4.dist-info/top_level.txt
odoo14_addon_l10n_fr_department_delivery-14.0.1.0.1.dev4.dist-info/RECORD
